appkit_ui/__init__.py
appkit_ui/global_states.py
appkit_ui/styles.py
appkit_ui/components/__init__.py
appkit_ui/components/collabsible.py
appkit_ui/components/dialogs.py
appkit_ui/components/editor.py
appkit_ui/components/form_inputs.py
appkit_ui/components/header.py
appkit_ui-1.0.1.dist-info/METADATA
appkit_ui-1.0.1.dist-info/WHEEL
appkit_ui-1.0.1.dist-info/RECORD
